blockinfile/__init__.py
blockinfile/__main__.py
blockinfile/blockinfile.py
blockinfile-2.17.1.dist-info/METADATA
blockinfile-2.17.1.dist-info/WHEEL
blockinfile-2.17.1.dist-info/entry_points.txt
blockinfile-2.17.1.dist-info/licenses/COPYING
blockinfile-2.17.1.dist-info/RECORD
