Metadata-Version: 2.3
Name: blockinfile
Version: 2.17.1
Summary: blockinfile is a tool for editing automatically a text block surrounded by marker lines
Project-URL: Documentation, https://gitlab.com/hydrargyrum/blockinfile
Project-URL: Issues, https://gitlab.com/hydrargyrum/blockinfile/issues
Project-URL: Source, https://gitlab.com/hydrargyrum/blockinfile
Author-email: Hg <dev@indigo.re>
License-Expression: MIT
License-File: COPYING
Classifier: Development Status :: 5 - Production/Stable
Classifier: Environment :: Console
Classifier: Intended Audience :: Developers
Classifier: Intended Audience :: System Administrators
Classifier: License :: OSI Approved :: GNU General Public License v3 (GPLv3)
Classifier: Operating System :: OS Independent
Classifier: Programming Language :: Python
Classifier: Programming Language :: Python :: 3.7
Classifier: Programming Language :: Python :: 3.8
Classifier: Programming Language :: Python :: 3.9
Classifier: Programming Language :: Python :: 3.10
Classifier: Programming Language :: Python :: 3.11
Classifier: Topic :: Software Development :: Code Generators
Classifier: Topic :: Software Development :: Pre-processors
Classifier: Topic :: System :: Systems Administration
Classifier: Topic :: Text Processing :: General
Classifier: Topic :: Utilities
Requires-Python: >=3.7
Requires-Dist: pyyaml
